pypushwoosh/__init__.py
pypushwoosh/base.py
pypushwoosh/client.py
pypushwoosh/command.py
pypushwoosh/constants.py
pypushwoosh/exceptions.py
pypushwoosh/filter.py
pypushwoosh/notification.py
pypushwoosh/utils.py
pypushwoosh-0.3.1.dist-info/LICENSE
pypushwoosh-0.3.1.dist-info/METADATA
pypushwoosh-0.3.1.dist-info/WHEEL
pypushwoosh-0.3.1.dist-info/top_level.txt
pypushwoosh-0.3.1.dist-info/RECORD
