Metadata-Version: 2.1
Name: pypushwoosh
Version: 0.3.1
Summary: Python client for Pushwoosh
Home-page: https://github.com/Pushwoosh/pushwoosh-python-lib
Author: Konstantin Misyutin
Author-email: ikeeip@gmail.com
Maintainer: Konstantin Misyutin
Maintainer-email: ikeeip@gmail.com
License: MIT
Keywords: Pushwoosh
Platform: UNKNOWN
Classifier: Development Status :: 4 - Beta
Classifier: Environment :: Console
Classifier: Topic :: Software Development :: Libraries :: Python Modules
Classifier: Intended Audience :: Developers
Classifier: License :: OSI Approved :: MIT License
Classifier: Operating System :: OS Independent
Classifier: Programming Language :: Python
Classifier: Programming Language :: Python :: 2
Classifier: Programming Language :: Python :: 2.7
Classifier: Programming Language :: Python :: 3
Classifier: Programming Language :: Python :: 3.3
Classifier: Programming Language :: Python :: 3.4
Classifier: Programming Language :: Python :: 3.5
Classifier: Programming Language :: Python :: 3.6
Requires-Dist: six
Requires-Dist: requests
